Workbook

Sheet Roadmap
A1: Roadmap — Gesto (Faro Sistemas)
A2: SaaS de gestión comercial multi-tenant · Actualizado 2026-06-22 · Editá la columna Estado y la fecha al cerrar cada tarea
A4: ID | B4: Categoría | C4: Tarea | D4: Prioridad | E4: Estado | F4: Notas | G4: Actualizado
A5: 1 | B5: Infraestructura | C5: Stack Next.js 16 App Router + TypeScript strict + Turbopack | D5: — | E5: Hecho | G5: 2026-06-22
A6: 2 | B6: Infraestructura | C6: Tailwind v4 + shadcn/ui + Design System Brasas | D6: — | E6: Hecho | G6: 2026-06-22
A7: 3 | B7: Infraestructura | C7: Drizzle ORM + Supabase Postgres | D7: — | E7: Hecho | G7: 2026-06-22
A8: 4 | B8: Infraestructura | C8: Supabase Auth SSR + middleware de sesión | D8: — | E8: Hecho | G8: 2026-06-22
A9: 5 | B9: Infraestructura | C9: Framer Motion + command palette (cmdk) | D9: — | E9: Hecho | G9: 2026-06-22
A10: 6 | B10: Base de datos | C10: Schema multi-tenant (tenants, users, productos, clientes, ventas, pagos, CC) | D10: — | E10: Hecho | F10: 10 tablas (+ presupuestos) | G10: 2026-06-22
A11: 7 | B11: Base de datos | C11: Migraciones aplicadas en Supabase | D11: — | E11: Hecho | G11: 2026-06-22
A12: 8 | B12: Base de datos | C12: RLS multi-tenant (16 políticas, script defensivo) | D12: — | E12: Hecho | F12: byTenant() + RLS como red de seguridad | G12: 2026-06-22
A13: 9 | B13: Auth | C13: Login / Signup / Onboarding (crear tenant) | D13: — | E13: Hecho | G13: 2026-06-22
A14: 10 | B14: Auth | C14: Recuperar contraseña (forgot + reset) | D14: — | E14: Hecho | G14: 2026-06-22
A15: 11 | B15: Auth | C15: Auth callback PKCE + token_hash | D15: — | E15: Hecho | G15: 2026-06-22
A16: 12 | B16: Productos | C16: CRUD productos (stock kg/unidad, precios may/min) | D16: — | E16: Hecho | F16: Title Case, inputs vacíos no 0 | G16: 2026-06-22
A17: 13 | B17: Productos | C17: Carga rápida (scan → nombre → precio → siguiente) | D17: — | E17: Hecho | F17: /productos/carga-rapida | G17: 2026-06-22
A18: 14 | B18: Productos | C18: Importación CSV con preview y validación | D18: — | E18: Hecho | F18: lotes de 100, crea categorías | G18: 2026-06-22
A19: 15 | B19: Productos | C19: Categorías (CRUD + filtro en lista y POS) | D19: — | E19: Hecho | G19: 2026-06-22
A20: 16 | B20: Productos | C20: Grupos de variantes + sugerencia asistida | D20: — | E20: Hecho | G20: 2026-06-22
A21: 17 | B21: Productos | C21: Código PLU (plan balanza) | D21: — | E21: Hecho | G21: 2026-06-22
A22: 18 | B22: Productos | C22: Precios vivos (anti-inflación: margen + actualización masiva) | D22: Alta | E22: En progreso | F22: Falta QA en vivo los 3 planes; ver docs/context/precios.md | G22: 2026-06-22
A23: 19 | B23: Productos | C23: Alertas de stock bajo (banner/email cuando stock ≤ mínimo) | D23: Media | E23: Pendiente | F23: El campo existe, no dispara nada | G23: 2026-06-22
A24: 20 | B24: Productos | C24: Precios especiales por cliente | D24: Media | E24: Pendiente | F24: Mayoristas con acuerdos puntuales | G24: 2026-06-22
A25: 21 | B25: Clientes | C25: CRUD clientes + ficha con saldo CC | D25: — | E25: Hecho | F25: tipo, condición IVA, descuento | G25: 2026-06-22
A26: 22 | B26: Ventas / POS | C26: POS unificado mayorista + minorista (carrito Zustand) | D26: — | E26: Hecho | F26: split-screen | G26: 2026-06-22
A27: 23 | B27: Ventas / POS | C27: Scanner de código de barras (ZXing, cámara real) | D27: — | E27: Hecho | G27: 2026-06-22
A28: 24 | B28: Ventas / POS | C28: Métodos de pago (efectivo, transf, tarjeta, MP, cuenta corriente) | D28: — | E28: Hecho | G28: 2026-06-22
A29: 25 | B29: Ventas / POS | C29: Ticket 80mm + Remito A4 PDF (compartir / descargar) | D29: — | E29: Hecho | F29: @react-pdf/renderer | G29: 2026-06-22
A30: 26 | B30: Ventas / POS | C30: Atajos de teclado (F2 cobrar, Esc, Supr) | D30: — | E30: Hecho | G30: 2026-06-22
A31: 27 | B31: Ventas / POS | C31: Historial + detalle de venta (filtro por período) | D31: — | E31: Hecho | G31: 2026-06-22
A32: 28 | B32: Ventas / POS | C32: Descuentos en POS (% o $ por total) | D32: Media | E32: Pendiente | F32: Muy pedido en kioscos/carnicerías | G32: 2026-06-22
A33: 29 | B33: Ventas / POS | C33: Devoluciones / notas de crédito (reversar venta + ajuste stock) | D33: Media | E33: Pendiente | F33: Reversión de CC ya está hecha | G33: 2026-06-22
A34: 30 | B34: Ventas / POS | C34: Lector de códigos USB en POS desktop (Enter agrega el producto escaneado) | D34: — | E34: Hecho | F34: Minorista + mayorista; el lector tipo supermercado escribe el código y Enter lo suma al carrito | G34: 2026-06-22
A35: 31 | B35: Cuenta Corriente | C35: Movimientos + registrar pago + saldo en tiempo real | D35: — | E35: Hecho | F35: registrarPago atómico FOR UPDATE | G35: 2026-06-22
A36: 32 | B36: Cuenta Corriente | C36: Reversión de movimientos (transacción atómica) | D36: — | E36: Hecho | F36: motivo obligatorio | G36: 2026-06-22
A37: 33 | B37: Reportes | C37: KPIs por período + ranking top productos + métodos de pago | D37: — | E37: Hecho | F37: ventana de tiempo unificada | G37: 2026-06-22
A38: 34 | B38: Reportes | C38: Exportar a CSV | D38: — | E38: Hecho | G38: 2026-06-22
A39: 35 | B39: Presupuestos | C39: CRUD + PDF + estados + numeración atómica | D39: — | E39: Hecho | F39: db.transaction | G39: 2026-06-22
A40: 36 | B40: Presupuestos | C40: Plantillas de servicios (guardar/listar/usar) | D40: — | E40: Hecho | G40: 2026-06-22
A41: 37 | B41: Proveedores / Pedidos | C41: CRUD proveedores (markup, selector de país) | D41: — | E41: Hecho | G41: 2026-06-22
A42: 38 | B42: Proveedores / Pedidos | C42: Pedidos a proveedor (WhatsApp + recepción con ajuste de stock) | D42: — | E42: Hecho | G42: 2026-06-22
A43: 39 | B43: Configuración / Equipo | C43: Datos fiscales + canales + conectar/desconectar Mercado Pago | D43: — | E43: Hecho | G43: 2026-06-22
A44: 40 | B44: Configuración / Equipo | C44: Equipo: invitar por email, editar rol, eliminar | D44: — | E44: Hecho | G44: 2026-06-22
A45: 41 | B45: Configuración / Equipo | C45: Control de acceso por rol (requireAdmin, route group) | D45: — | E45: Hecho | F45: empleado solo POS+Historial+Productos | G45: 2026-06-22
A46: 42 | B46: UX / Diseño | C46: Design System Brasas v2 (paleta cálida + grain + gradientes) | D46: — | E46: Hecho | G46: 2026-06-22
A47: 43 | B47: UX / Diseño | C47: Sidebar + mobile bottom nav con FAB Vender | D47: — | E47: Hecho | G47: 2026-06-22
A48: 44 | B48: UX / Diseño | C48: Skeleton loaders (7 rutas) | D48: — | E48: Hecho | G48: 2026-06-22
A49: 45 | B49: UX / Diseño | C49: Command palette ⌘K | D49: — | E49: Hecho | G49: 2026-06-22
A50: 46 | B50: UX / Diseño | C50: Nomenclatura: los modos se presentan como 'versión' al usuario (Market, Servicios, etc.) | D50: — | E50: Hecho | F50: Landing (switcher, precios, cierre) + /planes + confirmación de transferencia; se usan los nombres reales de los planes (Market, no inventados como 'Kiosco') | G50: 2026-06-22
A51: 47 | B51: UX / Diseño | C51: Dark / light toggle | D51: Baja | E51: Pendiente | G51: 2026-06-22
A52: 48 | B52: Negocio SaaS | C52: 4 planes + Mercado Pago preapproval + webhook activación/suspensión | D52: — | E52: Hecho | F52: src/lib/planes.ts | G52: 2026-06-22
A53: 49 | B53: Negocio SaaS | C53: Cobro por transferencia (panel admin + aviso cliente + comprobante por email) | D53: — | E53: Hecho | F53: Activación manual 1-click; /admin/suscripciones; emails salen al cargar RESEND_API_KEY | G53: 2026-06-22
A54: 50 | B54: Negocio SaaS | C54: Cobro automático MP/Mobbex (CUIT Monotributo + cuenta) | D54: Alta | E54: En progreso | F54: Bloqueado: falta CUIT + cuenta. Mientras tanto se cobra por transferencia | G54: 2026-06-22
A55: 51 | B55: Negocio SaaS | C55: Panel super-admin (gestionar tenants, métricas cross-tenant) | D55: Media | E55: En progreso | F55: Panel /admin/suscripciones operativo; faltan métricas cross-tenant | G55: 2026-06-22
A56: 52 | B56: Negocio SaaS | C56: Catálogo global cross-tenant | D56: Baja | E56: Pendiente | F56: Necesita OK explícito antes de implementar | G56: 2026-06-22
A57: 53 | B57: Lanzamiento (bloqueante) | C57: Dominio propio (ej: usegesto.app) | D57: Alta | E57: Pendiente | F57: URL actual no es presentable | G57: 2026-06-22
A58: 54 | B58: Lanzamiento (bloqueante) | C58: SMTP con Resend (invitación, bienvenida, reset con branding) | D58: Alta | E58: Pendiente | F58: Cron listo; falta RESEND_API_KEY en Vercel (rotar la vieja) | G58: 2026-06-22
A59: 55 | B59: Lanzamiento (bloqueante) | C59: Landing page pública (adaptativa por versión + demo en vivo) | D59: Alta | E59: Hecho | F59: v3 'de oficio' LIVE: switcher de versiones auto-rotativo, demo POS con ticket de papel, foto real + captura de Gesto en celular, antes/después, FAQ, pricing al MEP, paleta terracota (sin neón), responsive mobile. Login rediseñado (split de marca) | G59: 2026-06-22
A60: 56 | B60: Lanzamiento (bloqueante) | C60: PWA manifest + iconos (192/512, apple-touch-icon) | D60: Alta | E60: Pendiente | F60: POS se usa en tablet/celular | G60: 2026-06-22
A61: 57 | B61: Lanzamiento (bloqueante) | C61: Términos de servicio + Política de privacidad | D61: Alta | E61: Hecho | F61: Páginas /legal/{terminos,privacidad,cookies,baja-de-datos} + links en footer + checkbox en signup. Prestador: Faro Sistemas (SIN datos fiscales por etapa pre-formalización; único contacto = email en constante CONTACTO_EMAIL, hoy el gmail). AL FORMALIZAR: cargar CUIT + domicilio + jurisdicción y que un abogado revise | G61: 2026-06-22
A62: 58 | B62: Calidad / Seguridad | C62: Bugs críticos corregidos (stock al vender, numeración, loop /planes) | D62: — | E62: Hecho | G62: 2026-06-22
A63: 59 | B63: Calidad / Seguridad | C63: ConfirmDialog reutilizable (reemplaza window.confirm en 9 comp.) | D63: — | E63: Hecho | G63: 2026-06-22
A64: 60 | B64: Calidad / Seguridad | C64: Verificar firma de webhook MP | D64: — | E64: Hecho | F64: Firma HMAC timing-safe + fail-closed en prod; cargar MP_WEBHOOK_SECRET en Vercel | G64: 2026-06-22
A65: 61 | B65: Calidad / Seguridad | C65: Auditoría de seguridad E2E + fixes (IDOR token MP, recibirPedido, escalación de rol, OAuth state, crons fail-closed, escape de emails) | D65: — | E65: Hecho | F65: Guard test anti-omisión de byTenant; ver project_gesto_seguridad. RLS no protege capa app (byTenant única defensa) | G65: 2026-06-22
A66: 62 | B66: Calidad / Seguridad | C66: Rate limiting en auth (login/signup) | D66: Media | E66: Pendiente | F66: ej: @upstash/ratelimit | G66: 2026-06-22
A67: 63 | B67: Calidad / Seguridad | C67: Tests de integración (flows de venta y producto) | D67: Media | E67: Pendiente | G67: 2026-06-22
A68: 64 | B68: Calidad / Seguridad | C68: Export de datos (CSV ventas / inventario) | D68: Media | E68: Pendiente | F68: Que el cliente no sienta lock-in | G68: 2026-06-22
A69: 65 | B69: Calidad / Seguridad | C69: Facturación AFIP (Tusfacturas.app, A/B) | D69: Media | E69: Pendiente | F69: Bloqueante segmento servicios/mayorista | G69: 2026-06-22
A70: 66 | B70: Calidad / Seguridad | C70: Historial de auditoría básico (quién creó/modificó) | D70: Baja | E70: Pendiente | F70: Mínimo en productos y ventas | G70: 2026-06-22
A71: 67 | B71: Legal / Fiscal | C71: CUIT + Monotributo (o Responsable Inscripto) | D71: Alta | E71: Pendiente | F71: Bloquea cobrar en regla; ojo el tope anual de Monotributo con ingresos SaaS recurrentes | G71: 2026-06-22
A72: 68 | B72: Legal / Fiscal | C72: Registro de bases de datos ante la AAIP (Ley 25.326) | D72: Media | E72: Pendiente | F72: Sos responsable de la PII de los clientes y de SUS clientes | G72: 2026-06-22
A73: 69 | B73: Legal / Fiscal | C73: Botón de baja + arrepentimiento de suscripción (Res. 424/2020) | D73: Media | E73: En progreso | F73: Ya existe cancelarSuscripcion + página /legal/baja-de-datos que explica el proceso; falta el botón de arrepentimiento bien visible | G73: 2026-06-22
A74: 70 | B74: Legal / Fiscal | C74: Cláusulas de transferencia internacional de datos | D74: Baja | E74: Pendiente | F74: Datos en AWS us-east-1; Ley 25.326 exige resguardos (EE.UU. no es país adecuado por defecto) | G74: 2026-06-22
A75: 71 | B75: Legal / Fiscal | C75: Estructura societaria (SAS) + acuerdo escrito con socio | D75: Media | E75: Pendiente | F75: Separa patrimonio del riesgo; formaliza la participación de Facu | G75: 2026-06-22
A76: 72 | B76: Legal / Fiscal | C76: Contrato de servicio / SLA con clientes | D76: Media | E76: Pendiente | F76: Dueño de los datos (el cliente), uptime, soporte, límite de responsabilidad | G76: 2026-06-22
A77: 73 | B77: Infra / Escalado | C77: Vercel Pro + Supabase Pro | D77: Alta | E77: Pendiente | F77: Vercel Hobby es no comercial; Supabase Free se pausa a los 7 días. Bloquea producción real | G77: 2026-06-22
A78: 74 | B78: Infra / Escalado | C78: Backups diarios + PITR + probar un restore | D78: Media | E78: Pendiente | F78: Un backup sin restore probado no es un backup | G78: 2026-06-22
A79: 75 | B79: Infra / Escalado | C79: Monitoreo: activar Sentry + uptime check | D79: Media | E79: Pendiente | F79: SENTRY_DSN ya está en el build, falta activarlo + un cron canario | G79: 2026-06-22
... A87: 83 | B87: Versiones / Verticales | C87: Gesto Atmosféricos: historial, agenda y pedidos para días futuros + arreglar ruta en Maps | D87: Alta | E87: Hecho | F87: Historial ya existía; AGENDA (navegación entre días) + pedidos para días futuros HECHO. Maps ARREGLADO: campo 'ubicación exacta' (link de Maps) por pedido; geo.ts extrae coordenadas del link y la ruta usa el punto exacto en vez del texto. Migración 0010 en dev+prod | G87: 2026-06-22
A88: 84 | B88: Roadmap v2 | C88: Modificadores por ítem en POS (extras, variantes) | D88: Baja | E88: Pendiente | G88: 2026-06-22
A89: 85 | B89: Roadmap v2 | C89: App mobile nativa con Capacitor (offline first) | D89: Baja | E89: Pendiente | G89: 2026-06-22
A90: 86 | B90: Roadmap v2 | C90: Notificaciones push (stock, pedidos) | D90: Baja | E90: Pendiente | G90: 2026-06-22
A91: 87 | B91: Roadmap v2 | C91: Dashboard financiero avanzado (márgenes, rentabilidad) | D91: Baja | E91: Pendiente | G91: 2026-06-22
A92: 88 | B92: Roadmap v2 | C92: Multi-sucursal (varios locales bajo una cuenta madre) | D92: Baja | E92: Pendiente | G92: 2026-06-22
A93: 89 | B93: Marketing / Conversión | C93: Registro en mini-wizard modal (versión -> cuenta), sin mandar al login frío | D93: Alta | E93: Hecho | F93: Modal in-page (no popup) que abren los CTA 'Empezá gratis'. Paso 1 elegís versión, paso 2 creás cuenta; la versión se hereda al onboarding | G93: 2026-06-22
A94: 90 | B94: Marketing / Conversión | C94: Login con Google (OAuth) | D94: Alta | E94: En progreso | F94: Código cableado en el wizard y disponible. FALTA: habilitar el provider Google en Supabase (Auth -> Providers) con credenciales de Google Cloud Console | G94: 2026-06-22
A95: 91 | B95: Marketing / Conversión | C95: Botón de WhatsApp flotante en la landing | D95: Alta | E95: Hecho | F95: Sugerido por Deepseek y Gemini. FALTA: reemplazar el número placeholder por el real | G95: 2026-06-22
A96: 92 | B96: Marketing / Conversión | C96: Landing pages por vertical (/market, /atmosfericos, /balanza) para pauta en Meta Ads | D96: Alta | E96: Pendiente | F96: Gemini: la página de destino tiene que hablarle solo a ese rubro para no diluir la conversión | G96: 2026-06-22
A97: 93 | B97: Marketing / Conversión | C97: Dominio propio (ej. gesto.com.ar) apuntado en Vercel | D97: Alta | E97: Pendiente | F97: Gemini: faro-sistemas.vercel.app no transmite 'Gesto' y resta confianza | G97: 2026-06-22
A98: 94 | B98: Marketing / Conversión | C98: Nav de la landing con Versiones y Ayuda (hoy solo Precios) | D98: Media | E98: Pendiente | F98: Deepseek | G98: 2026-06-22
A99: 95 | B99: Marketing / Conversión | C99: Sello 'datos encriptados' + destacar '14 días sin tarjeta' como badge | D99: Media | E99: Pendiente | F99: Deepseek: confianza sin necesitar testimonios | G99: 2026-06-22
A100: 96 | B100: Marketing / Conversión | C100: Testimonios / casos de éxito | D100: Media | E100: Pendiente | F100: Dejar el espacio diseñado y llenarlo con los primeros clientes reales (no inventar) | G100: 2026-06-22
A101: 97 | B101: Marketing / Conversión | C101: Decidir precio en ARS prominente y USD como referencia | D101: Media | E101: Pendiente | F101: Deepseek; toca la decisión de negocio de cobro al MEP en USD | G101: 2026-06-22

Sheet Resumen
A1: Resumen del Roadmap
A3: Estado | B3: Cantidad | C3: % del total
A4: Hecho | B4: =COUNTIF(Roadmap!$E$5:$E$101,A4) | C4: =IFERROR(B4/$B$7,0)
A5: En progreso | B5: =COUNTIF(Roadmap!$E$5:$E$101,A5) | C5: =IFERROR(B5/$B$7,0)
A6: Pendiente | B6: =COUNTIF(Roadmap!$E$5:$E$101,A6) | C6: =IFERROR(B6/$B$7,0)
A7: TOTAL | B7: =COUNTA(Roadmap!$E$5:$E$101)
A10: Categoría | B10: Hecho | C10: Pendiente/En curso
A11: Infraestructura | B11: =COUNTIFS(Roadmap!$B$5:$B$101,A11,Roadmap!$E$5:$E$101,"Hecho") | C11: =COUNTIFS(Roadmap!$B$5:$B$101,A11)-B11
A12: Base de datos | B12: =COUNTIFS(Roadmap!$B$5:$B$101,A12,Roadmap!$E$5:$E$101,"Hecho") | C12: =COUNTIFS(Roadmap!$B$5:$B$101,A12)-B12
A13: Auth | B13: =COUNTIFS(Roadmap!$B$5:$B$101,A13,Roadmap!$E$5:$E$101,"Hecho") | C13: =COUNTIFS(Roadmap!$B$5:$B$101,A13)-B13
A14: Productos | B14: =COUNTIFS(Roadmap!$B$5:$B$101,A14,Roadmap!$E$5:$E$101,"Hecho") | C14: =COUNTIFS(Roadmap!$B$5:$B$101,A14)-B14
A15: Clientes | B15: =COUNTIFS(Roadmap!$B$5:$B$101,A15,Roadmap!$E$5:$E$101,"Hecho") | C15: =COUNTIFS(Roadmap!$B$5:$B$101,A15)-B15
A16: Ventas / POS | B16: =COUNTIFS(Roadmap!$B$5:$B$101,A16,Roadmap!$E$5:$E$101,"Hecho") | C16: =COUNTIFS(Roadmap!$B$5:$B$101,A16)-B16
A17: Cuenta Corriente | B17: =COUNTIFS(Roadmap!$B$5:$B$101,A17,Roadmap!$E$5:$E$101,"Hecho") | C17: =COUNTIFS(Roadmap!$B$5:$B$101,A17)-B17
A18: Reportes | B18: =COUNTIFS(Roadmap!$B$5:$B$101,A18,Roadmap!$E$5:$E$101,"Hecho") | C18: =COUNTIFS(Roadmap!$B$5:$B$101,A18)-B18
A19: Presupuestos | B19: =COUNTIFS(Roadmap!$B$5:$B$101,A19,Roadmap!$E$5:$E$101,"Hecho") | C19: =COUNTIFS(Roadmap!$B$5:$B$101,A19)-B19
A20: Proveedores / Pedidos | B20: =COUNTIFS(Roadmap!$B$5:$B$101,A20,Roadmap!$E$5:$E$101,"Hecho") | C20: =COUNTIFS(Roadmap!$B$5:$B$101,A20)-B20
A21: Configuración / Equipo | B21: =COUNTIFS(Roadmap!$B$5:$B$101,A21,Roadmap!$E$5:$E$101,"Hecho") | C21: =COUNTIFS(Roadmap!$B$5:$B$101,A21)-B21
A22: UX / Diseño | B22: =COUNTIFS(Roadmap!$B$5:$B$101,A22,Roadmap!$E$5:$E$101,"Hecho") | C22: =COUNTIFS(Roadmap!$B$5:$B$101,A22)-B22
... A31: Marketing / Conversión | B31: =COUNTIFS(Roadmap!$B$5:$B$101,A31,Roadmap!$E$5:$E$101,"Hecho") | C31: =COUNTIFS(Roadmap!$B$5:$B$101,A31)-B31
